DockerJiaochengCYuyanBianchengWangFix1/README.md
DockerJiaochengCYuyanBianchengWangFix1/__init__.py
DockerJiaochengCYuyanBianchengWangFix1/__main__.py
DockerJiaochengCYuyanBianchengWangFix1/file.epub
DockerJiaochengCYuyanBianchengWangFix1/index.html
DockerJiaochengCYuyanBianchengWangFix1/css/__init__.py
DockerJiaochengCYuyanBianchengWangFix1/css/annotations.css
DockerJiaochengCYuyanBianchengWangFix1/css/main.css
DockerJiaochengCYuyanBianchengWangFix1/css/normalize.css
DockerJiaochengCYuyanBianchengWangFix1/css/popup.css
DockerJiaochengCYuyanBianchengWangFix1/font/__init__.py
DockerJiaochengCYuyanBianchengWangFix1/font/fontello.eot
DockerJiaochengCYuyanBianchengWangFix1/font/fontello.svg
DockerJiaochengCYuyanBianchengWangFix1/font/fontello.ttf
DockerJiaochengCYuyanBianchengWangFix1/font/fontello.woff
DockerJiaochengCYuyanBianchengWangFix1/img/__init__.py
DockerJiaochengCYuyanBianchengWangFix1/img/annotator-glyph-sprite.png
DockerJiaochengCYuyanBianchengWangFix1/img/annotator-icon-sprite.png
DockerJiaochengCYuyanBianchengWangFix1/img/apple-touch-icon.png
DockerJiaochengCYuyanBianchengWangFix1/img/cancelfullscreen.png
DockerJiaochengCYuyanBianchengWangFix1/img/close.png
DockerJiaochengCYuyanBianchengWangFix1/img/fullscreen.png
DockerJiaochengCYuyanBianchengWangFix1/img/loader.gif
DockerJiaochengCYuyanBianchengWangFix1/img/menu-icon.png
DockerJiaochengCYuyanBianchengWangFix1/img/save.png
DockerJiaochengCYuyanBianchengWangFix1/img/saved.png
DockerJiaochengCYuyanBianchengWangFix1/img/settings-s.png
DockerJiaochengCYuyanBianchengWangFix1/img/settings.png
DockerJiaochengCYuyanBianchengWangFix1/img/star.png
DockerJiaochengCYuyanBianchengWangFix1/js/__init__.py
DockerJiaochengCYuyanBianchengWangFix1/js/epub.js
DockerJiaochengCYuyanBianchengWangFix1/js/epub.min.js
DockerJiaochengCYuyanBianchengWangFix1/js/epub.min.map
DockerJiaochengCYuyanBianchengWangFix1/js/hooks.min.js
DockerJiaochengCYuyanBianchengWangFix1/js/hooks.min.map
docker_jiaocheng_c_yuyan_biancheng_wang_fix1-2025.3.24.1.dist-info/METADATA
docker_jiaocheng_c_yuyan_biancheng_wang_fix1-2025.3.24.1.dist-info/WHEEL
docker_jiaocheng_c_yuyan_biancheng_wang_fix1-2025.3.24.1.dist-info/entry_points.txt
docker_jiaocheng_c_yuyan_biancheng_wang_fix1-2025.3.24.1.dist-info/top_level.txt
docker_jiaocheng_c_yuyan_biancheng_wang_fix1-2025.3.24.1.dist-info/RECORD
